ParallelizeSSH/Command.py
ParallelizeSSH/SSH.py
ParallelizeSSH/SSHConn.py
ParallelizeSSH/Targets.py
ParallelizeSSH/__init__.py
ParallelizeSSH/config.py
ParallelizeSSH-0.0.2.dist-info/LICENSE
ParallelizeSSH-0.0.2.dist-info/METADATA
ParallelizeSSH-0.0.2.dist-info/WHEEL
ParallelizeSSH-0.0.2.dist-info/top_level.txt
ParallelizeSSH-0.0.2.dist-info/RECORD
