Metadata-Version: 2.1
Name: ParallelizeSSH
Version: 0.0.2
Summary: Simple Parallel SSH based on Paramiko backend.
Home-page: https://github.com/Rahul-RB/paramiko-parallel-ssh
Author: Rahul R Bharadwaj
License: UNKNOWN
Platform: UNKNOWN
Classifier: Programming Language :: Python :: 3
Classifier: License :: OSI Approved :: GNU General Public License v3 (GPLv3)
Classifier: Operating System :: OS Independent
Requires-Python: >=3.6
